pytest_md_report/__init__.py
pytest_md_report/__version__.py
pytest_md_report/_const.py
pytest_md_report/_style_filter.py
pytest_md_report/plugin.py
pytest_md_report/py.typed
pytest_md_report-0.6.2.dist-info/LICENSE
pytest_md_report-0.6.2.dist-info/METADATA
pytest_md_report-0.6.2.dist-info/WHEEL
pytest_md_report-0.6.2.dist-info/entry_points.txt
pytest_md_report-0.6.2.dist-info/top_level.txt
pytest_md_report-0.6.2.dist-info/RECORD
