Metadata-Version: 2.1
Name: pytest-md-report
Version: 0.6.2
Summary: A pytest plugin to generate test outcomes reports with markdown table format.
Home-page: https://github.com/thombashi/pytest-md-report
Author: Tsuyoshi Hombashi
Author-email: tsuyoshi.hombashi@gmail.com
License: MIT License
Project-URL: Changlog, https://github.com/thombashi/pytest-md-report/releases
Project-URL: Source, https://github.com/thombashi/pytest-md-report
Project-URL: Tracker, https://github.com/thombashi/pytest-md-report/issues
Keywords: pytest,plugin,markdown
Classifier: Development Status :: 4 - Beta
Classifier: Environment :: Plugins
Classifier: Framework :: Pytest
Classifier: Intended Audience :: Developers
Classifier: License :: OSI Approved :: MIT License
Classifier: Operating System :: OS Independent
Classifier: Programming Language :: Python :: 3
Classifier: Programming Language :: Python :: 3.7
Classifier: Programming Language :: Python :: 3.8
Classifier: Programming Language :: Python :: 3.9
Classifier: Programming Language :: Python :: 3.10
Classifier: Programming Language :: Python :: 3.11
Classifier: Programming Language :: Python :: 3.12
Classifier: Programming Language :: Python :: 3 :: Only
Classifier: Programming Language :: Python :: Implementation :: CPython
Classifier: Programming Language :: Python :: Implementation :: PyPy
Classifier: Topic :: Software Development :: Quality Assurance
Classifier: Topic :: Software Development :: Testing
Classifier: Topic :: Text Processing
Classifier: Topic :: Text Processing :: Markup :: Markdown
Classifier: Typing :: Typed
Requires-Python: >=3.7
License-File: LICENSE
Requires-Dist: pytablewriter <2,>=1.2.0
Requires-Dist: pytest !=6.0.0,<9,>=3.3.2
Requires-Dist: tcolorpy <1,>=0.0.5
Requires-Dist: typepy <2,>=1.1.1
Provides-Extra: test
